prompt_defender_aws_defences/__init__.py
prompt_defender_aws_defences/wall/__init__.py
prompt_defender_aws_defences/wall/pii_detection.py
prompt_defender_aws_defences/wall/sagemaker_inference.py
prompt_defender_aws_defences/wall/shared.py
prompt_defender_aws_defences-0.1.26.dist-info/METADATA
prompt_defender_aws_defences-0.1.26.dist-info/WHEEL
prompt_defender_aws_defences-0.1.26.dist-info/RECORD
