Metadata-Version: 2.1
Name: prompt-defender-aws-defences
Version: 0.1.26
Summary: Prompt Defender. A package to help you defend against prompt injection attacks.
Author: Daniel Llewellyn
Author-email: admin@safetorun.com
Requires-Python: >=3.9,<4.0
Classifier: Programming Language :: Python :: 3
Classifier: Programming Language :: Python :: 3.9
Classifier: Programming Language :: Python :: 3.10
Classifier: Programming Language :: Python :: 3.11
Classifier: Programming Language :: Python :: 3.12
Requires-Dist: boto3 (>=1.34.0,<2.0.0)
Requires-Dist: pydantic (>=2.6.3,<3.0.0)
Requires-Dist: pydantic_core (>=2.16.3,<3.0.0)
